Youtube_Downloader/__init__.py
Youtube_Downloader/youtube.py
youtube_video-1.0.0.dist-info/LICENSE
youtube_video-1.0.0.dist-info/METADATA
youtube_video-1.0.0.dist-info/WHEEL
youtube_video-1.0.0.dist-info/top_level.txt
youtube_video-1.0.0.dist-info/RECORD
