Metadata-Version: 2.1
Name: youtube-video
Version: 1.0.0
Summary: Download Video Yotube
Author: Farooq
Keywords: python,download,youtube
License-File: LICENSE
Requires-Dist: pytube
